kids/__init__.py
kids/sh/__init__.py
kids/sh/sh.py
kids/sh/tests/__init__.py
kids/sh/tests/test_cmd.py
kids/sh/tests/test_wrap.py
kids.sh-0.0.8.dist-info/DESCRIPTION.rst
kids.sh-0.0.8.dist-info/LICENSE.txt
kids.sh-0.0.8.dist-info/METADATA
kids.sh-0.0.8.dist-info/RECORD
kids.sh-0.0.8.dist-info/WHEEL
kids.sh-0.0.8.dist-info/metadata.json
kids.sh-0.0.8.dist-info/top_level.txt
